m4b_merge/__init__.py
m4b_merge/__main__.py
m4b_merge/audible_helper.py
m4b_merge/config.py
m4b_merge/conftest.py
m4b_merge/helpers.py
m4b_merge/m4b_helper.py
m4b_merge-0.5.3.dist-info/LICENSE
m4b_merge-0.5.3.dist-info/METADATA
m4b_merge-0.5.3.dist-info/WHEEL
m4b_merge-0.5.3.dist-info/entry_points.txt
m4b_merge-0.5.3.dist-info/top_level.txt
m4b_merge-0.5.3.dist-info/RECORD
