Metadata-Version: 2.1
Name: m4b-merge
Version: 0.5.3
Summary: A tool to standardize audiobook files into single m4b files with clean metadata based on Audible and chapters.
Home-page: https://github.com/djdembeck/m4b-merge
Author: David Dembeck
Author-email: dembeck.david@protonmail.com
Project-URL: Bug Tracker, https://github.com/djdembeck/m4b-merge/issues
Classifier: Programming Language :: Python :: 3.8
Classifier: Programming Language :: Python :: 3.9
Classifier: Programming Language :: Python :: 3.10
Classifier: Programming Language :: Python :: 3.11
Classifier: License :: OSI Approved :: GNU General Public License v3 (GPLv3)
Classifier: Operating System :: OS Independent
Requires-Python: >=3.7
License-File: LICENSE
Requires-Dist: appdirs>=1.4.4
Requires-Dist: pathvalidate>=2.4.1
Requires-Dist: pydub>=0.25.1
Requires-Dist: requests>=2.24.0
